{
	"info": {
		"_postman_id": "9a9300da-45b4-41f9-8e20-c09872b757b2",
		"name": "Actividad3",
		"schema": "https://schema.getpostman.com/json/collection/v2.1.0/collection.json",
		"_exporter_id": "27564569"
	},
	"item": [
		{
			"name": "Create User",
			"request": {
				"method": "POST",
				"header": [],
				"body": {
					"mode": "raw",
					"raw": "{\n    \"name\": \"test\",\n    \"email\": \"test@test.com\",\n    \"password\": \"1234\",\n    \"bio\": \"Holi\"\n}",
					"options": {
						"raw": {
							"language": "json"
						}
					}
				},
				"url": {
					"raw": "localhost:8000/api/users",
					"host": [
						"localhost"
					],
					"port": "8000",
					"path": [
						"api",
						"users"
					]
				}
			},
			"response": []
		},
		{
			"name": "Login",
			"request": {
				"method": "POST",
				"header": [],
				"body": {
					"mode": "raw",
					"raw": "{\n    \"email\": \"test@test.com\",\n    \"password\": \"1234\"\n}",
					"options": {
						"raw": {
							"language": "json"
						}
					}
				},
				"url": {
					"raw": "localhost:8000/api/login",
					"host": [
						"localhost"
					],
					"port": "8000",
					"path": [
						"api",
						"login"
					]
				}
			},
			"response": []
		},
		{
			"name": "New Post: Success",
			"request": {
				"auth": {
					"type": "bearer",
					"bearer": [
						{
							"key": "token",
							"value": "eyJhbGciOiJIUzI1NiIsInR5cCI6IkpXVCJ9.eyJzdWIiOiI2NDZjZTczMWVkZTY2YTU2Yzc3ODU2NjgiLCJleHAiOjE2ODQ4NTg2ODI0MzksImlhdCI6MTY4NDg1ODY4MH0.kw5VDAgO_tJwfSqN-lNWfI6NJVUdLdKRWC5QV5gqVQE",
							"type": "string"
						}
					]
				},
				"method": "POST",
				"header": [],
				"body": {
					"mode": "raw",
					"raw": "{\n    \"title\": \"Testing\",\n    \"text\": \"Test text\",\n    \"author\": \"Me\"\n}",
					"options": {
						"raw": {
							"language": "json"
						}
					}
				},
				"url": {
					"raw": "localhost:8000/api/posts",
					"host": [
						"localhost"
					],
					"port": "8000",
					"path": [
						"api",
						"posts"
					]
				}
			},
			"response": []
		},
		{
			"name": "Get All: Token error",
			"protocolProfileBehavior": {
				"disableBodyPruning": true
			},
			"request": {
				"method": "GET",
				"header": [],
				"body": {
					"mode": "raw",
					"raw": "{\n    \"title\": \"Testing\",\n    \"text\": \"Test text\",\n    \"author\": \"Me\"\n}",
					"options": {
						"raw": {
							"language": "json"
						}
					}
				},
				"url": {
					"raw": "localhost:8000/api/posts",
					"host": [
						"localhost"
					],
					"port": "8000",
					"path": [
						"api",
						"posts"
					]
				}
			},
			"response": []
		},
		{
			"name": "Get All: Success",
			"protocolProfileBehavior": {
				"disableBodyPruning": true
			},
			"request": {
				"auth": {
					"type": "bearer",
					"bearer": [
						{
							"key": "token",
							"value": "eyJhbGciOiJIUzI1NiIsInR5cCI6IkpXVCJ9.eyJzdWIiOiI2NDZjZTczMWVkZTY2YTU2Yzc3ODU2NjgiLCJleHAiOjE2ODQ4NTg2ODI0MzksImlhdCI6MTY4NDg1ODY4MH0.kw5VDAgO_tJwfSqN-lNWfI6NJVUdLdKRWC5QV5gqVQE",
							"type": "string"
						}
					]
				},
				"method": "GET",
				"header": [],
				"body": {
					"mode": "raw",
					"raw": "{\n    \"title\": \"Testing\",\n    \"text\": \"Test text\",\n    \"author\": \"Me\"\n}",
					"options": {
						"raw": {
							"language": "json"
						}
					}
				},
				"url": {
					"raw": "localhost:8000/api/posts",
					"host": [
						"localhost"
					],
					"port": "8000",
					"path": [
						"api",
						"posts"
					]
				}
			},
			"response": []
		}
	]
}